knorket_diarize/__init__.py
knorket_diarize/cli.py
knorket_diarize/helpers.py
knorket_diarize/main.py
knorket_diarize-0.1.0.dist-info/LICENSE
knorket_diarize-0.1.0.dist-info/METADATA
knorket_diarize-0.1.0.dist-info/WHEEL
knorket_diarize-0.1.0.dist-info/entry_points.txt
knorket_diarize-0.1.0.dist-info/top_level.txt
knorket_diarize-0.1.0.dist-info/RECORD
